{
  "lastUpdated": "2026-02-20T04:18:30.979Z",
  "releases": [
    {
      "slug": "sumac",
      "name": "Sumac",
      "edxPlatformRef": "open-release/sumac.master",
      "filtersRef": "v1.11.0",
      "eventsRef": "v9.15.0"
    },
    {
      "slug": "teak",
      "name": "Teak",
      "edxPlatformRef": "release/teak",
      "filtersRef": "v2.0.1",
      "eventsRef": "v10.2.0"
    },
    {
      "slug": "ulmo",
      "name": "Ulmo",
      "edxPlatformRef": "release/ulmo",
      "filtersRef": "v2.1.0",
      "eventsRef": "v10.5.0"
    }
  ]
}